gba/Builder.py
gba/Enumerations.py
gba/Model.py
gba/Reaction.py
gba/Species.py
gba/__init__.py
gba-0.6.0.dist-info/licenses/LICENSE
gba-0.6.0.dist-info/METADATA
gba-0.6.0.dist-info/WHEEL
gba-0.6.0.dist-info/top_level.txt
gba-0.6.0.dist-info/RECORD
