Metadata-Version: 2.4
Name: gba
Version: 0.6.0
Summary: gbapy (Growth Balance Analysis for Python)
Home-page: https://github.com/charlesrocabert/gbapy
Author: Charles Rocabert
Author-email: charles.rocabert@hhu.de
Maintainer: Furkan Mert
License: GNU General Public License v3 (GPLv3)
Project-URL: Source, https://github.com/charlesrocabert/gbapy
Keywords: constraint-based-modeling growth-balance-analysis self-replicating-model systems-biology metabolic-network resource-allocation cellular-economics kinetic-modeling first-prnciples simulation evolutionary-algorithms predictive-evolution
Classifier: Development Status :: 4 - Beta
Classifier: Programming Language :: Python :: 3
Classifier: License :: OSI Approved :: GNU General Public License v3 (GPLv3)
Classifier: Operating System :: OS Independent
Classifier: Intended Audience :: Science/Research
Classifier: Topic :: Scientific/Engineering :: Mathematics
Requires-Python: >=3
License-File: LICENSE
Requires-Dist: cobra
Requires-Dist: molmass
Requires-Dist: numpy
Requires-Dist: pandas
Requires-Dist: gurobipy
Requires-Dist: Bio
Requires-Dist: IPython
Requires-Dist: plotly
Dynamic: author
Dynamic: author-email
Dynamic: classifier
Dynamic: description
Dynamic: description-content-type
Dynamic: home-page
Dynamic: keywords
Dynamic: license
Dynamic: license-file
Dynamic: maintainer
Dynamic: project-url
Dynamic: requires-dist
Dynamic: requires-python
Dynamic: summary
